lemonpy/__init__.py
lemonpy-0.0.3.dist-info/WHEEL
lemonpy-0.0.3.dist-info/METADATA
lemonpy-0.0.3.dist-info/RECORD
